bourbaki/__init__.py
bourbaki/application/__init__.py
bourbaki/application/multiprocessing.py
bourbaki/application/namespace.py
bourbaki/application/paths.py
bourbaki/application/reutils.py
bourbaki/application/cli/__init__.py
bourbaki/application/cli/actions.py
bourbaki/application/cli/decorators.py
bourbaki/application/cli/helpers.py
bourbaki/application/cli/main.py
bourbaki/application/cli/signatures.py
bourbaki/application/completion/__init__.py
bourbaki/application/completion/bourbaki_bash_completion_helpers.sh
bourbaki/application/completion/compgen_python_classpaths.py
bourbaki/application/completion/completers.py
bourbaki/application/config/__init__.py
bourbaki/application/config/exceptions.py
bourbaki/application/config/ini.py
bourbaki/application/config/io.py
bourbaki/application/config/python.py
bourbaki/application/logging/__init__.py
bourbaki/application/logging/analysis.py
bourbaki/application/logging/config.py
bourbaki/application/logging/defaults.py
bourbaki/application/logging/handlers.py
bourbaki/application/logging/helpers.py
bourbaki/application/logging/interface.py
bourbaki/application/logging/loggers.py
bourbaki/application/logging/regexes.py
bourbaki/application/logging/timing.py
bourbaki/application/typed_io/__init__.py
bourbaki/application/typed_io/cli_complete.py
bourbaki/application/typed_io/cli_nargs_.py
bourbaki/application/typed_io/cli_parse.py
bourbaki/application/typed_io/cli_repr_.py
bourbaki/application/typed_io/config_decode.py
bourbaki/application/typed_io/config_encode.py
bourbaki/application/typed_io/config_repr_.py
bourbaki/application/typed_io/env_parse.py
bourbaki/application/typed_io/exceptions.py
bourbaki/application/typed_io/inflation.py
bourbaki/application/typed_io/main.py
bourbaki/application/typed_io/parsers.py
bourbaki/application/typed_io/utils.py
bourbaki/application/typed_io/env/__init__.py
bourbaki/application/typed_io/env/env_parse.py
bourbaki.application-0.10.12.dist-info/LICENSE
bourbaki.application-0.10.12.dist-info/METADATA
bourbaki.application-0.10.12.dist-info/WHEEL
bourbaki.application-0.10.12.dist-info/entry_points.txt
bourbaki.application-0.10.12.dist-info/top_level.txt
bourbaki.application-0.10.12.dist-info/zip-safe
bourbaki.application-0.10.12.dist-info/RECORD
