Metadata-Version: 2.1
Name: bourbaki.application
Version: 0.10.12
Summary: UNKNOWN
Home-page: https://github.com/bourbaki-py
Author: Matthew Hawthorn
Author-email: hawthorn.matthew@gmail.com
License: Apache License 2.0
Platform: MacOS X
Platform: Linux
Classifier: Programming Language :: Python :: 3
Classifier: Programming Language :: Python :: 3.6
Classifier: Programming Language :: Python :: 3.7
Classifier: License :: OSI Approved :: Apache Software License
Classifier: Operating System :: POSIX :: Linux
Classifier: Operating System :: MacOS :: MacOS X
Classifier: Topic :: Software Development :: Libraries :: Python Modules
Classifier: Topic :: Software Development :: Code Generators
Classifier: Topic :: Utilities
Classifier: Typing :: Typed
Requires-Dist: pkginfo
Requires-Dist: multipledispatch (>=0.4.9)
Requires-Dist: ujson
Requires-Dist: toml
Requires-Dist: PyYAML (>=3.12)
Requires-Dist: typing-inspect
Requires-Dist: bourbaki.introspection (>=0.5.1)
